data_by_dorofeev/__init__.py
data_by_dorofeev/data.py
data_by_dorofeev/main.py
data_by_dorofeev-0.0.6.dist-info/LICENSE
data_by_dorofeev-0.0.6.dist-info/METADATA
data_by_dorofeev-0.0.6.dist-info/WHEEL
data_by_dorofeev-0.0.6.dist-info/top_level.txt
data_by_dorofeev-0.0.6.dist-info/RECORD
