Metadata-Version: 2.1
Name: data_by_dorofeev
Version: 0.0.6
Summary: By Dorofeev
Author-email: Andrey <dorofeevav1149@gmail.com>
Project-URL: Homepage, https://turnmanedition.github.io/IsTericad.com/
Project-URL: Issues, https://github.com/TurnManEDITION/IsTericad.com
Classifier: Programming Language :: Python :: 3
Classifier: License :: OSI Approved :: MIT License
Classifier: Operating System :: OS Independent
Requires-Python: >=3.8
License-File: LICENSE
